intrieri1998/__init__.py
intrieri1998/fig5.py
intrieri1998/fig6.py
intrieri1998/fig8.py
intrieri1998/info.py
intrieri1998/version.py
intrieri1998/clean/fig3.csv
intrieri1998/clean/fig4.csv
intrieri1998/clean/fig5.csv
intrieri1998/clean/fig6.csv
intrieri1998/clean/fig7.csv
intrieri1998/clean/fig8.csv
intrieri1998/clean/info.json
intrieri1998/clean/readme.rst
intrieri1998/clean/table.csv
intrieri1998-1.3.0.dist-info/AUTHORS.rst
intrieri1998-1.3.0.dist-info/LICENSE
intrieri1998-1.3.0.dist-info/METADATA
intrieri1998-1.3.0.dist-info/WHEEL
intrieri1998-1.3.0.dist-info/top_level.txt
intrieri1998-1.3.0.dist-info/RECORD
